{
  "main": {
    "id": "eeb79f2151146120",
    "type": "split",
    "children": [
      {
        "id": "fe803b48cf903a1c",
        "type": "tabs",
        "children": [
          {
            "id": "d66b77668ae5e7a4",
            "type": "leaf",
            "state": {
              "type": "markdown",
              "state": {
                "file": "01. Operating Systems/Unix/00.01. Команды терминала/Who команда терминала.md",
                "mode": "source",
                "source": false
              },
              "icon": "lucide-file",
              "title": "Who команда терминала"
            }
          },
          {
            "id": "dde4ad30b42a7365",
            "type": "leaf",
            "state": {
              "type": "markdown",
              "state": {
                "file": "Авторизация.md",
                "mode": "source",
                "source": false
              },
              "icon": "lucide-file",
              "title": "Авторизация"
            }
          },
          {
            "id": "8d4d6368ec53c784",
            "type": "leaf",
            "state": {
              "type": "markdown",
              "state": {
                "file": "08. Databases/01. SQL/01. Основы/Вычисляемое поле SQL.md",
                "mode": "source",
                "source": false
              },
              "icon": "lucide-file",
              "title": "Вычисляемое поле SQL"
            }
          },
          {
            "id": "13ccf0ab723a9b99",
            "type": "leaf",
            "state": {
              "type": "markdown",
              "state": {
                "file": "08. Databases/01. SQL/01. Основы/Вычисляемое поле SQL.md",
                "mode": "source",
                "source": false
              },
              "icon": "lucide-file",
              "title": "Вычисляемое поле SQL"
            }
          }
        ],
        "currentTab": 3
      }
    ],
    "direction": "vertical"
  },
  "left": {
    "id": "2f17fd6323c13c1f",
    "type": "split",
    "children": [
      {
        "id": "5b56d9a30c8d21c3",
        "type": "tabs",
        "children": [
          {
            "id": "e0335aabd4c36c4b",
            "type": "leaf",
            "state": {
              "type": "file-explorer",
              "state": {
                "sortOrder": "alphabetical",
                "autoReveal": false
              },
              "icon": "lucide-folder-closed",
              "title": "Файловый менеджер"
            }
          },
          {
            "id": "d967c165546965c8",
            "type": "leaf",
            "state": {
              "type": "search",
              "state": {
                "query": "",
                "matchingCase": false,
                "explainSearch": false,
                "collapseAll": false,
                "extraContext": false,
                "sortOrder": "alphabetical"
              },
              "icon": "lucide-search",
              "title": "Поиск"
            }
          },
          {
            "id": "24cf6603ae63ae8e",
            "type": "leaf",
            "state": {
              "type": "bookmarks",
              "state": {},
              "icon": "lucide-bookmark",
              "title": "Закладки"
            }
          }
        ]
      }
    ],
    "direction": "horizontal",
    "width": 246.5
  },
  "right": {
    "id": "d039eb2cfe35e9ff",
    "type": "split",
    "children": [
      {
        "id": "c758e34f2709ee55",
        "type": "tabs",
        "children": [
          {
            "id": "26f9be9936fe8fa6",
            "type": "leaf",
            "state": {
              "type": "backlink",
              "state": {
                "collapseAll": false,
                "extraContext": false,
                "sortOrder": "alphabetical",
                "showSearch": false,
                "searchQuery": "",
                "backlinkCollapsed": false,
                "unlinkedCollapsed": true
              },
              "icon": "links-coming-in",
              "title": "Обратные ссылки"
            }
          },
          {
            "id": "4cb8611aa9fc129c",
            "type": "leaf",
            "state": {
              "type": "outgoing-link",
              "state": {
                "linksCollapsed": false,
                "unlinkedCollapsed": true
              },
              "icon": "links-going-out",
              "title": "Исходящие ссылки"
            }
          },
          {
            "id": "ea543d7ebd47ba7a",
            "type": "leaf",
            "state": {
              "type": "tag",
              "state": {
                "sortOrder": "frequency",
                "useHierarchy": true,
                "showSearch": false,
                "searchQuery": ""
              },
              "icon": "lucide-tags",
              "title": "Теги"
            }
          },
          {
            "id": "8a77a520ebb06208",
            "type": "leaf",
            "state": {
              "type": "all-properties",
              "state": {
                "sortOrder": "frequency",
                "showSearch": false,
                "searchQuery": ""
              },
              "icon": "lucide-archive",
              "title": "Все свойства"
            }
          },
          {
            "id": "b87b3b490a15173d",
            "type": "leaf",
            "state": {
              "type": "outline",
              "state": {
                "file": "гойда.md",
                "followCursor": false,
                "showSearch": false,
                "searchQuery": ""
              },
              "icon": "lucide-list",
              "title": "Структура гойда"
            }
          },
          {
            "id": "cb92030a3a0abb72",
            "type": "leaf",
            "state": {
              "type": "review-queue-list-view",
              "state": {},
              "icon": "lucide-ghost",
              "title": "review-queue-list-view"
            }
          }
        ],
        "currentTab": 5
      }
    ],
    "direction": "horizontal",
    "width": 300,
    "collapsed": true
  },
  "left-ribbon": {
    "hiddenItems": {
      "switcher:Меню быстрого перехода": false,
      "graph:Граф": false,
      "canvas:Создать новый холст": false,
      "daily-notes:Сегодняшняя заметка": false,
      "templates:Вставить шаблон": false,
      "command-palette:Открыть палитру команд": false,
      "bases:Создать новую базу": false,
      "obsidian-spaced-repetition:Изучать карточки": false
    }
  },
  "active": "13ccf0ab723a9b99",
  "lastOpenFiles": [
    "08. Databases/01. SQL/01. Основы/Подзапрос SQL.md",
    "08. Databases/01. SQL/01. Основы/Вычисляемое поле SQL.md",
    "08. Databases/01. SQL/01. Основы",
    "08. Databases/01. SQL/01. Основы/Склеивание строк SQL.md",
    "08. Databases/01. SQL",
    "08. Databases/01. SQL/00. Операторы SQL/WHERE оператор SQL.md",
    "08. Databases/01. SQL/00. Операторы SQL/SELECT оператор SQL.md",
    "08. Databases/01. SQL/00. Операторы SQL/ORDER BY оператор SQL.md",
    "08. Databases/01. SQL/00. Операторы SQL/AS оператора SELECT SQL.md",
    "08. Databases/01. SQL/00. Операторы SQL/DISTINCT оператора SELECT.md",
    "08. Databases/01. SQL/00. Операторы SQL/FROM оператор SQL.md",
    "Аутентификация.md",
    "Авторизация.md",
    "02. Computer Networks/02. Канальный уровень/02.03. Адресация, построение соединений/MAC-адрес.md",
    "08. Databases",
    "01. Operating Systems/Unix/02. Файловая система, права и атрибуты/02.01. Структура и ссылки/Proc (VFS).md",
    "02. Computer Networks/03. Сетевой уровень/03.02. IP-адрес, протокол IP/IP-адрес.md",
    "02. Computer Networks/04. Транспортный уровень/04.01. Порты, сокеты, UDP/Порт.md",
    "03. Docker/03. Драйверы хранилища и тома/Директория слоя (overlay2).md",
    "02. Computer Networks/02. Канальный уровень/02.04. Wi-Fi/Базовый набор сервисов Wi-Fi.md",
    "01. Operating Systems/Unix/00.01. Команды терминала/Who команда терминала.md",
    "01. Operating Systems/Unix/00.01. Команды терминала/Sudo команда терминала.md",
    "02. Computer Networks/05. Прикладной уровень/05.02. HTTP/05.02.01. Основы/Статусы HTTP.md",
    "02. Computer Networks/02. Канальный уровень/02.04. Wi-Fi/Роуминг.md",
    "02. Computer Networks/02. Канальный уровень/02.04. Wi-Fi/Режимы аутентификации Wi-Fi.md",
    "Идентификация.md",
    "02. Computer Networks/05. Прикладной уровень/05.02. HTTP/05.02.02. Proxy/Анонимный прокси (Anonymous Proxy).md",
    "02. Computer Networks/05. Прикладной уровень/05.02. HTTP/05.02.01. Основы/Протокол HTTP.md",
    "02. Computer Networks/05. Прикладной уровень/05.02. HTTP/05.02.02. Proxy",
    "02. Computer Networks/05. Прикладной уровень/05.02. HTTP/05.02.01. Основы",
    "02. Computer Networks/05. Прикладной уровень/05.02. HTTP",
    "02. Computer Networks/05. Прикладной уровень/05.01. Основы, DNS",
    "02. Computer Networks/05. Прикладной уровень",
    "02. Computer Networks/04. Транспортный уровень/04.03. NAT и Firewall",
    "02. Computer Networks/04. Транспортный уровень/04.02. Протокол TCP/04.02.02. Перегрузка"
  ]
}